cookiesamurai/__init__.py
cookiesamurai/__main__.py
cookiesamurai/main.py
cookiesamurai-1.0.0a1.dist-info/METADATA
cookiesamurai-1.0.0a1.dist-info/WHEEL
cookiesamurai-1.0.0a1.dist-info/entry_points.txt
cookiesamurai-1.0.0a1.dist-info/top_level.txt
cookiesamurai-1.0.0a1.dist-info/RECORD
