Metadata-Version: 2.1
Name: cookiesamurai
Version: 1.0.0a1
Summary: A wrapper around cookiesamurai to allow for conditional questions.
Author-email: Younes Strittmatter <younes_strittmatter@brown.edu>
License: MIT License
Project-URL: repository, https://github.com/younesStrittmatter/cookiesamurai
Requires-Python: <4,>=3.8
Requires-Dist: cookiecutter
Requires-Dist: requests
